README.rst
setup.py
novault/Keccak.py
novault/__init__.py
novault/__main__.py
novault/__version__
novault/ed25519.py
novault/novault.py
novault/x.py
novault.egg-info/PKG-INFO
novault.egg-info/SOURCES.txt
novault.egg-info/dependency_links.txt
novault.egg-info/requires.txt
novault.egg-info/top_level.txt