Metadata-Version: 1.1
Name: novault
Version: 0.300
Summary: Stateless Password Manager and Brain Wallet
Home-page: https://github.com/novault/novault
Author: Avner Herskovits
Author-email: novault.dev@gmail.com
License: MIT
Download-URL: https://github.com/novault/novault/tarball/0.300
Platform: UNKNOWN
Classifier: Development Status :: 4 - Beta
Classifier: Environment :: Other Environment
Classifier: Intended Audience :: Developers
Classifier: Intended Audience :: End Users/Desktop
Classifier: Intended Audience :: Information Technology
Classifier: Intended Audience :: System Administrators
Classifier: License :: OSI Approved :: MIT License
Classifier: Operating System :: OS Independent
Classifier: Programming Language :: Python
Classifier: Topic :: Software Development :: Libraries
Classifier: Topic :: Security
Classifier: Topic :: Security :: Cryptography
Classifier: Topic :: Utilities
